rocksdb3-0.1.0.dist-info/METADATA
rocksdb3-0.1.0.dist-info/WHEEL
rocksdb3/__init__.py
rocksdb3/rocksdb3.cpython-38-x86_64-linux-gnu.so
rocksdb3-0.1.0.dist-info/RECORD
