Metadata-Version: 2.1
Name: rocksdb3
Version: 0.1.0
Classifier: Development Status :: 3 - Alpha
Classifier: Operating System :: MacOS
Classifier: Operating System :: Microsoft :: Windows
Classifier: Operating System :: POSIX :: Linux
Classifier: Programming Language :: Python
Classifier: Programming Language :: Python :: 3 :: Only
Classifier: Programming Language :: Python :: 3.5
Classifier: Programming Language :: Python :: 3.6
Classifier: Programming Language :: Python :: 3.7
Classifier: Programming Language :: Python :: 3.8
Classifier: Programming Language :: Python :: 3.9
Classifier: Programming Language :: Python :: 3.10
Summary: Python bindings for the Rust rocksdb crate
Home-Page: https://github.com/xyb/rocksdb3
Author: Xie Yanbo <xieyanbo@gmail.com>
Author-email: Xie Yanbo <xieyanbo@gmail.com>
License: Apache-2.0
Project-URL: Source Code, https://github.com/xyb/rocksdb3
